mozdownload/__init__.py
mozdownload/cli.py
mozdownload/errors.py
mozdownload/factory.py
mozdownload/parser.py
mozdownload/scraper.py
mozdownload/treeherder.py
mozdownload/utils.py
mozdownload-1.30.0.dist-info/licenses/LICENSE.txt
mozdownload-1.30.0.dist-info/METADATA
mozdownload-1.30.0.dist-info/WHEEL
mozdownload-1.30.0.dist-info/entry_points.txt
mozdownload-1.30.0.dist-info/top_level.txt
mozdownload-1.30.0.dist-info/RECORD
