Metadata-Version: 2.4
Name: mozdownload
Version: 1.30.0
Summary: Script to download builds for Firefox and Thunderbird from the Mozilla server.
Home-page: https://github.com/mozilla/mozdownload
Author: Mozilla Automation and Testing Team
Author-email: tools@lists.mozilla.com
License: Mozilla Public License 2.0 (MPL 2.0)
Keywords: mozilla
Classifier: Development Status :: 5 - Production/Stable
Classifier: Environment :: Console
Classifier: Intended Audience :: Developers
Classifier: Intended Audience :: End Users/Desktop
Classifier: License :: OSI Approved :: Mozilla Public License 2.0 (MPL 2.0)
Classifier: Operating System :: OS Independent
Classifier: Topic :: Software Development :: Testing
Classifier: Topic :: System :: Software Distribution
Classifier: Topic :: Utilities
Classifier: Programming Language :: Python :: 3 :: Only
Classifier: Programming Language :: Python :: 3.9
Classifier: Programming Language :: Python :: 3.10
Classifier: Programming Language :: Python :: 3.11
Classifier: Programming Language :: Python :: 3.12
Classifier: Programming Language :: Python :: 3.13
License-File: LICENSE.txt
Requires-Dist: mozinfo>=1.0.0
Requires-Dist: mozilla-version>=2.0.0
Requires-Dist: progressbar2>=3.34.3
Requires-Dist: redo==3.0.0
Requires-Dist: requests<3.0.0,>=2.21.0
Requires-Dist: treeherder-client<6.0.0,>=5.0.0
Dynamic: author
Dynamic: author-email
Dynamic: classifier
Dynamic: description
Dynamic: description-content-type
Dynamic: home-page
Dynamic: keywords
Dynamic: license
Dynamic: license-file
Dynamic: requires-dist
Dynamic: summary
